pycasty/Game.py
pycasty/__init__.py
pycasty/map.py
pycasty/object_handler.py
pycasty/object_renderer.py
pycasty/player.py
pycasty/raycasting.py
pycasty/settings.py
pycasty/sprite_object.py
pycasty/resources/sprites/animated_sprites/green_light/0.png
pycasty/resources/sprites/animated_sprites/green_light/1.png
pycasty/resources/sprites/animated_sprites/green_light/3.png
pycasty/resources/sprites/animated_sprites/green_light/4.png
pycasty/resources/sprites/animated_sprites/red_light/0.png
pycasty/resources/sprites/animated_sprites/red_light/1.png
pycasty/resources/sprites/animated_sprites/red_light/2.png
pycasty/resources/sprites/animated_sprites/red_light/3.png
pycasty/resources/sprites/static_sprites/candlebra.png
pycasty/resources/textures/1.png
pycasty/resources/textures/2.png
pycasty/resources/textures/3.png
pycasty/resources/textures/4.png
pycasty/resources/textures/5.png
pycasty/resources/textures/sky.png
pycasty-0.1.2.dist-info/METADATA
pycasty-0.1.2.dist-info/WHEEL
pycasty-0.1.2.dist-info/top_level.txt
pycasty-0.1.2.dist-info/RECORD
